folha_de_ponto/__init__.py
folha_de_ponto-0.0.1.dist-info/METADATA
folha_de_ponto-0.0.1.dist-info/WHEEL
folha_de_ponto-0.0.1.dist-info/top_level.txt
folha_de_ponto-0.0.1.dist-info/RECORD
