Metadata-Version: 2.1
Name: folha-de-ponto
Version: 0.0.1
Summary: Folha de ponto Python package
Author: Victor Cruz
Author-email: gil.victor1998@gmail.com
License: MIT
